{
    "token": "4BCB",
    "courses": [
        {
            "token": "BC2",
            "name": "Biochemie 2",
            "dates": [
                {
                    "dayOfWeek": 0,
                    "timeSlot": 0,
                    "prof": "FRC",
                    "location": "G137 "
                }
            ]
        },
        {
            "token": "BCP",
            "name": "Biochemie - Praktikum",
            "dates": [
                {
                    "dayOfWeek": 1,
                    "timeSlot": 0,
                    "prof": "STN",
                    "location": "G211 "
                },
                {
                    "dayOfWeek": 1,
                    "timeSlot": 0,
                    "prof": "STN",
                    "location": "H0908 "
                },
                {
                    "dayOfWeek": 1,
                    "timeSlot": 1,
                    "prof": "STN",
                    "location": "G211 "
                },
                {
                    "dayOfWeek": 1,
                    "timeSlot": 2,
                    "prof": "STN",
                    "location": "G211 "
                },
                {
                    "dayOfWeek": 1,
                    "timeSlot": 3,
                    "prof": "STN",
                    "location": "G211 "
                }
            ]
        },
        {
            "token": "BOP",
            "name": "Bioorganisches Praktikum",
            "dates": [
                {
                    "dayOfWeek": 2,
                    "timeSlot": 0,
                    "prof": "SCD",
                    "location": "G118 "
                },
                {
                    "dayOfWeek": 2,
                    "timeSlot": 1,
                    "prof": "SCD",
                    "location": "G118 "
                },
                {
                    "dayOfWeek": 2,
                    "timeSlot": 2,
                    "prof": "SCD",
                    "location": "G118 "
                }
            ]
        },
        {
            "token": "MBP",
            "name": "Mikrobiologisches Praktikum",
            "dates": [
                {
                    "dayOfWeek": 3,
                    "timeSlot": 0,
                    "prof": "MCK",
                    "location": "G213 "
                },
                {
                    "dayOfWeek": 3,
                    "timeSlot": 1,
                    "prof": "MCK",
                    "location": "G213 "
                },
                {
                    "dayOfWeek": 3,
                    "timeSlot": 2,
                    "prof": "MCK",
                    "location": "G213 "
                },
                {
                    "dayOfWeek": 3,
                    "timeSlot": 3,
                    "prof": "MCK",
                    "location": "G213 "
                }
            ]
        },
        {
            "token": "MIB",
            "name": "Mikrobiologie",
            "dates": [
                {
                    "dayOfWeek": 0,
                    "timeSlot": 1,
                    "prof": "MCK",
                    "location": "H0407 "
                },
                {
                    "dayOfWeek": 4,
                    "timeSlot": 0,
                    "prof": "MCK",
                    "location": "G045 "
                }
            ]
        },
        {
            "token": "MOB",
            "name": "Molekularbiologie",
            "dates": [
                {
                    "dayOfWeek": 4,
                    "timeSlot": 1,
                    "prof": "KIO",
                    "location": "G137 "
                }
            ]
        },
        {
            "token": "BOC",
            "name": "Bioorganische Chemie",
            "dates": [
                {
                    "dayOfWeek": 0,
                    "timeSlot": 3,
                    "prof": "SCD",
                    "location": "G045 "
                },
                {
                    "dayOfWeek": 2,
                    "timeSlot": 3,
                    "prof": "SCD",
                    "location": "G045 "
                }
            ]
        }
    ]
}