{
    "token": "FRA",
    "name": "Dr. Oliver Franke",
    "email": "o.franke",
    "website": null,
    "associations": {
        "faculty": {
            "token": "W",
            "name": "Wirtschaftsingenieurwesen",
            "link": "http://www.wing.hs-mannheim.de/"
        },
        "institutes": null
    },
    "extra": "",
    "location": "Geb. L (11), Raum 157",
    "phone": "(0621)-292-6152",
    "appointments": "mittwochs 11:30- 13:00Uhr, während der vorlesungsfreien Zeit nur n. Vereinbarung"
}